{
  "timestamp": "2026-03-27T00:00:00Z",
  "from_agent": "Nova",
  "to_agent": "Cipher",
  "objective_achieved": [
    "Successfully connected database X",
    "Generated reports for Q1"
  ],
  "files_modified": [
    "/workspace/domains/marketing/campaign_q1.md"
  ],
  "blockers": [
    "Awaiting API key for external service Y"
  ],
  "next_steps": [
    "Review report formatting",
    "Deploy changes to Vercel"
  ],
  "crucial_context": "The Supabase Anon Key is injected via NEXT_PUBLIC_ env variable, do not hardcode."
}
